commonstuff/__init__.py
commonstuff/admin.py
commonstuff/filters.py
commonstuff/middleware.py
commonstuff/models.py
commonstuff/models_base.py
commonstuff/settings.py
commonstuff/storage.py
commonstuff/str_utils.py
commonstuff/tests.py
commonstuff/views.py
commonstuff/locale/ru/LC_MESSAGES/django.mo
commonstuff/locale/ru/LC_MESSAGES/django.po
commonstuff/management/__init__.py
commonstuff/management/commands/__init__.py
commonstuff/management/commands/allurls.py
commonstuff/management/commands/checkemailautocorrection.py
commonstuff/management/commands/ckeditoruploads.py
commonstuff/management/commands/djangover.py
commonstuff/migrations/0001_initial.py
commonstuff/migrations/0002_auto_20190214_1438.py
commonstuff/migrations/__init__.py
commonstuff/templatetags/__init__.py
commonstuff/templatetags/settings_value.py
commonstuff/templatetags/site_tools.py
commonstuff/templatetags/str_tools.py
django_commonstuff-0.8.5.dist-info/LICENSE
django_commonstuff-0.8.5.dist-info/METADATA
django_commonstuff-0.8.5.dist-info/WHEEL
django_commonstuff-0.8.5.dist-info/top_level.txt
django_commonstuff-0.8.5.dist-info/RECORD
